selenium_extension/SelEx.py
selenium_extension/SeleniumExtension.py
selenium_extension/__init__.py
selenium_extension-1.9.1.dist-info/LICENSE.txt
selenium_extension-1.9.1.dist-info/METADATA
selenium_extension-1.9.1.dist-info/WHEEL
selenium_extension-1.9.1.dist-info/top_level.txt
selenium_extension-1.9.1.dist-info/RECORD
