Metadata-Version: 2.1
Name: selenium-extension
Version: 1.9.1
Summary: Provides additional methods for selenium automation
Home-page: UNKNOWN
Author: CyberSecure
Author-email: krishj8000@gmail.com
License: MIT
Platform: UNKNOWN
Classifier: License :: OSI Approved :: MIT License
Classifier: Programming Language :: Python :: 3
Classifier: Programming Language :: Python :: 3.7
Requires-Dist: selenium
Requires-Dist: webdriver-manager
Requires-Dist: pytest-xdist
